multireg/MultiReg.py
multireg/Utils.py
multireg/__init__.py
multireg/napari.yaml
multireg-0.0.18.dist-info/LICENSE
multireg-0.0.18.dist-info/METADATA
multireg-0.0.18.dist-info/WHEEL
multireg-0.0.18.dist-info/entry_points.txt
multireg-0.0.18.dist-info/top_level.txt
multireg-0.0.18.dist-info/RECORD
