Metadata-Version: 2.1
Name: multireg
Version: 0.0.18
Summary: Registration of 3D multiplex images with one common chanel
Home-page: https://gitlab.pasteur.fr/gletort/multireg
Author: Gaëlle Letort
Author-email: gaelle.letort@pasteur.fr
License: BSD-3-Clause
Project-URL: Bug Tracker, https://gitlab.pasteur.fr/gletort/multireg/issues
Project-URL: Documentation, https://gitlab.pasteur.fr/gletort/multireg#README.md
Project-URL: Source Code, https://gitlab.pasteur.fr/gletort/multireg
Classifier: Framework :: napari
Classifier: Intended Audience :: Developers
Classifier: License :: OSI Approved :: BSD License
Classifier: Operating System :: OS Independent
Classifier: Programming Language :: Python
Classifier: Programming Language :: Python :: 3
Classifier: Programming Language :: Python :: 3 :: Only
Classifier: Programming Language :: Python :: 3.8
Classifier: Programming Language :: Python :: 3.9
Classifier: Topic :: Scientific/Engineering :: Image Processing
Requires-Python: >=3.8
License-File: LICENSE
Requires-Dist: numpy
Requires-Dist: napari<=0.4.18
Requires-Dist: magicgui
Requires-Dist: qtpy
Requires-Dist: pyqt5
Requires-Dist: tifffile
Requires-Dist: imaris-ims-file-reader
Requires-Dist: czifile
Requires-Dist: itk==5.3.0
Requires-Dist: itk-registration
Requires-Dist: itk-elastix
